mysqlsync/__init__.py
mysqlsync/mysqlsync.py
mysqlsync-1.0.1.dist-info/LICENSE
mysqlsync-1.0.1.dist-info/METADATA
mysqlsync-1.0.1.dist-info/WHEEL
mysqlsync-1.0.1.dist-info/top_level.txt
mysqlsync-1.0.1.dist-info/RECORD
