Metadata-Version: 2.1
Name: mysqlsync
Version: 1.0.1
Summary: A package to sync mysql from json
Home-page: https://github.com/harishuw/mysqlsync
Author: Harish U Warrier
Author-email: huwz1it@gmail.com
License: UNKNOWN
Platform: UNKNOWN
Classifier: Programming Language :: Python :: 3
Classifier: License :: OSI Approved :: MIT License
Classifier: Operating System :: OS Independent
Requires-Dist: mysql-connector-python
